string_decorator/NumericParser.py
string_decorator/__init__.py
string_decorator-0.4.0.dist-info/LICENSE
string_decorator-0.4.0.dist-info/METADATA
string_decorator-0.4.0.dist-info/WHEEL
string_decorator-0.4.0.dist-info/top_level.txt
string_decorator-0.4.0.dist-info/RECORD
