Metadata-Version: 2.1
Name: string-decorator
Version: 0.4.0
Summary: Python package for playing with strings
Author: imEternity
License: MIT License
Project-URL: Homepage, https://github.com/eternity2745/string-decorator#readme
Project-URL: Repository, https://github.com/eternity2745/string-decorator
Keywords: string,decorator,case,changer
Classifier: Development Status :: 5 - Production/Stable
Classifier: Environment :: Console
Classifier: License :: OSI Approved :: MIT License
Classifier: Programming Language :: Python :: 3
Classifier: Topic :: Utilities
Classifier: Topic :: Text Processing :: General
License-File: LICENSE
Requires-Dist: colorama
Requires-Dist: pyparsing
